setup.cfg
setup.py
ex_aws/ex_aws.py
ex_aws.egg-info/PKG-INFO
ex_aws.egg-info/SOURCES.txt
ex_aws.egg-info/dependency_links.txt
ex_aws.egg-info/not-zip-safe
ex_aws.egg-info/top_level.txt