Metadata-Version: 2.1
Name: ex-aws
Version: 0.0
Summary: ex_aws
Author-email: ilapronin0700@gmail.com
